UPSmodules/UPSKeys.py
UPSmodules/UPSgui.py
UPSmodules/UPSmodule.py
UPSmodules/__init__.py
UPSmodules/env.py
rickslab_ups_utils-1.3.0.data/data/share/man/man1/ups-daemon.1
rickslab_ups_utils-1.3.0.data/data/share/man/man1/ups-ls.1
rickslab_ups_utils-1.3.0.data/data/share/man/man1/ups-mon.1
rickslab_ups_utils-1.3.0.data/data/share/man/man4/ups-config.json.4
rickslab_ups_utils-1.3.0.data/data/share/man/man4/ups-util.ini.4
rickslab_ups_utils-1.3.0.data/data/share/rickslab-ups-utils/config/ups-config.json.template
rickslab_ups_utils-1.3.0.data/data/share/rickslab-ups-utils/config/ups-utils.ini.template
rickslab_ups_utils-1.3.0.data/data/share/rickslab-ups-utils/doc/LICENSE
rickslab_ups_utils-1.3.0.data/data/share/rickslab-ups-utils/doc/README.md
rickslab_ups_utils-1.3.0.data/data/share/rickslab-ups-utils/icons/ups-utils-monitor.icon.png
rickslab_ups_utils-1.3.0.data/scripts/cancelShutdownBOINC.sh
rickslab_ups_utils-1.3.0.data/scripts/pauseBOINC.sh
rickslab_ups_utils-1.3.0.data/scripts/quitBOINC.sh
rickslab_ups_utils-1.3.0.data/scripts/resumeBOINC.sh
rickslab_ups_utils-1.3.0.data/scripts/shutdownBOINC.sh
rickslab_ups_utils-1.3.0.data/scripts/ups-daemon
rickslab_ups_utils-1.3.0.data/scripts/ups-ls
rickslab_ups_utils-1.3.0.data/scripts/ups-mon
rickslab_ups_utils-1.3.0.data/scripts/ups-monitor
rickslab_ups_utils-1.3.0.dist-info/LICENSE
rickslab_ups_utils-1.3.0.dist-info/METADATA
rickslab_ups_utils-1.3.0.dist-info/WHEEL
rickslab_ups_utils-1.3.0.dist-info/top_level.txt
rickslab_ups_utils-1.3.0.dist-info/RECORD
