Metadata-Version: 2.1
Name: rickslab-ups-utils
Version: 1.3.0
Summary: Ricks-Lab UPS Utilities
Home-page: https://github.com/Ricks-Lab/ups-utils
Author: RicksLabs
Author-email: rueikes.homelab@gmail.com
License: GPL-3
Project-URL: Bug Tracker, https://github.com/Ricks-Lab/ups-utils/issues
Project-URL: Documentation, https://github.com/Ricks-Lab/ups-utils/
Project-URL: Source Code, https://github.com/Ricks-Lab/ups-utils
Keywords: ups system monitoring apc eaton linux boinc
Platform: posix
Classifier: Development Status :: 5 - Production/Stable
Classifier: Operating System :: POSIX
Classifier: Natural Language :: English
Classifier: Programming Language :: Python :: 3
Classifier: Topic :: System :: Power (UPS)
Classifier: Topic :: System :: Monitoring
Classifier: License :: OSI Approved :: GNU General Public License v3 (GPLv3)
Requires-Python: >=3.6
Requires-Dist: pytz (>=2019.3)
